rest_celery/__init__.py
rest_celery/admin.py
rest_celery/apps.py
rest_celery/models.py
rest_celery/serializers.py
rest_celery/swagger.py
rest_celery/tests.py
rest_celery/views.py
rest_celery/migrations/__init__.py
rest_celery-0.1.0.dist-info/METADATA
rest_celery-0.1.0.dist-info/WHEEL
rest_celery-0.1.0.dist-info/top_level.txt
rest_celery-0.1.0.dist-info/RECORD
